service/__init__.py
service/main.cpython-311-x86_64-linux-gnu.so
start_service_web-0.1.7.dist-info/METADATA
start_service_web-0.1.7.dist-info/WHEEL
start_service_web-0.1.7.dist-info/top_level.txt
start_service_web-0.1.7.dist-info/RECORD
