Metadata-Version: 2.4
Name: start-service-web
Version: 0.1.7
Summary: start-service-web
Author-email: LauLe <levanlau.net@email.com>
License: MIT
Requires-Python: >=3.8
